tests/__init__.py
tests/test_config.py
tests/test_file_organizer.py
yasfs/__init__.py
yasfs/__main__.py
yasfs/config.py
yasfs/file_organizer.py
yasfs-1.0.dist-info/LICENSE
yasfs-1.0.dist-info/METADATA
yasfs-1.0.dist-info/WHEEL
yasfs-1.0.dist-info/entry_points.txt
yasfs-1.0.dist-info/top_level.txt
yasfs-1.0.dist-info/RECORD
