Metadata-Version: 2.1
Name: yasfs
Version: 1.0
Summary: Python-based command-line tool that organizes and sorts files by their extension types
Home-page: https://github.com/ashaider/yet-another-simple-file-sorter/
Author: ashaider
Author-email: ahmedsyedh1+gh@gmail.com
License: MIT
Classifier: Programming Language :: Python :: 3
Classifier: License :: OSI Approved :: MIT License
Classifier: Operating System :: OS Independent
Requires-Python: >=3.8
License-File: LICENSE
